apac/__init__.py
apac/core.py
apac/mesh.py
apac/util.py
apac-0.1.0.dist-info/METADATA
apac-0.1.0.dist-info/WHEEL
apac-0.1.0.dist-info/top_level.txt
apac-0.1.0.dist-info/RECORD
