Metadata-Version: 2.1
Name: apac
Version: 0.1.0
Summary: Automatically parcellate putative human core using myelin content and curvature
Home-page: https://github.com/Raon31/apac
Author: Kyoungseob Byeon
Author-email: brec4u@gmail.com
License: UNKNOWN
Platform: UNKNOWN
Classifier: Programming Language :: Python :: 3
Classifier: Operating System :: OS Independent
